doc901.py
doc901-0.2.dist-info/entry_points.txt
doc901-0.2.dist-info/WHEEL
doc901-0.2.dist-info/METADATA
doc901-0.2.dist-info/RECORD
