Metadata-Version: 2.3
Name: doc901
Version: 0.2
Summary: Enforce docstrings on complex function and methods
Author-email: Martín Gaitán <marting@shiphero.com>
Requires-Python: >=3.9
Requires-Dist: ruff
Requires-Dist: rich
Project-URL: Home, https://github.com/shiphero/doc901
